PyZureML/__init__.py
PyZureML/endpoints.py
PyZureML-1.0.5.dist-info/DESCRIPTION.rst
PyZureML-1.0.5.dist-info/METADATA
PyZureML-1.0.5.dist-info/RECORD
PyZureML-1.0.5.dist-info/WHEEL
PyZureML-1.0.5.dist-info/metadata.json
PyZureML-1.0.5.dist-info/top_level.txt
