Metadata-Version: 2.0
Name: PyZureML
Version: 1.0.5
Summary: Python wrapper for the Microsoft Azure Machine Learning webservice endpoint API.
Home-page: https://github.com/marcardioid/PyZureML
Author: Marc Sleegers
Author-email: mail@marcsleegers.com
License: MIT
Keywords: microsoft azure machine learning webservice endpoint api wrapper
Platform: UNKNOWN
Classifier: Development Status :: 5 - Production/Stable
Classifier: Intended Audience :: Developers
Classifier: Topic :: Software Development :: Libraries :: Python Modules
Classifier: License :: OSI Approved :: MIT License
Classifier: Programming Language :: Python :: 3
Classifier: Programming Language :: Python :: 3.1
Classifier: Programming Language :: Python :: 3.2
Classifier: Programming Language :: Python :: 3.3
Classifier: Programming Language :: Python :: 3.4
Classifier: Programming Language :: Python :: 3.5
Requires-Dist: requests
